onecite/__init__.py
onecite/cli.py
onecite/core.py
onecite/exceptions.py
onecite/pipeline.py
onecite/templates/book.yaml
onecite/templates/conference_paper.yaml
onecite/templates/dataset.yaml
onecite/templates/journal_article_full.yaml
onecite/templates/software.yaml
onecite/templates/thesis.yaml
onecite-0.0.12.dist-info/licenses/LICENSE
onecite-0.0.12.dist-info/METADATA
onecite-0.0.12.dist-info/WHEEL
onecite-0.0.12.dist-info/entry_points.txt
onecite-0.0.12.dist-info/top_level.txt
onecite-0.0.12.dist-info/RECORD
