Metadata-Version: 2.4
Name: onecite
Version: 0.0.12
Summary: Universal citation management and academic reference toolkit
Author-email: He Zhiang <ang@hezhiang.com>
License: MIT
Project-URL: Homepage, https://github.com/HzaCode/OneCite
Project-URL: Documentation, https://onecite.readthedocs.io
Project-URL: Repository, https://github.com/HzaCode/OneCite
Project-URL: Issues, https://github.com/HzaCode/OneCite/issues
Project-URL: Changelog, https://github.com/HzaCode/OneCite/blob/main/docs/changelog.rst
Project-URL: Bug Tracker, https://github.com/HzaCode/OneCite/issues
Keywords: citation,bibliography,bibtex,academic,reference,doi,arxiv
Classifier: Development Status :: 4 - Beta
Classifier: Intended Audience :: Science/Research
Classifier: Intended Audience :: Developers
Classifier: License :: OSI Approved :: MIT License
Classifier: Programming Language :: Python :: 3
Classifier: Programming Language :: Python :: 3.10
Classifier: Programming Language :: Python :: 3.11
Classifier: Topic :: Software Development :: Libraries :: Python Modules
Classifier: Topic :: Text Processing :: Markup
Requires-Python: >=3.10
License-File: LICENSE
Requires-Dist: requests>=2.25.0
Requires-Dist: beautifulsoup4>=4.9.0
Requires-Dist: bibtexparser>=1.2.0
Requires-Dist: thefuzz>=0.19.0
Requires-Dist: scholarly>=1.5.0
Requires-Dist: pyyaml>=5.4.0
Requires-Dist: feedparser>=6.0.0
Provides-Extra: dev
Requires-Dist: pytest>=6.0; extra == "dev"
Requires-Dist: pytest-cov>=2.10; extra == "dev"
Requires-Dist: flake8>=3.8; extra == "dev"
Requires-Dist: black>=20.8b1; extra == "dev"
Dynamic: license-file
